unigui/__init__.py
unigui/colorscheme.py
unigui/pygamedisplay.py
unigui/widget.py
unigui/fonts/04b30-75.bdf
unigui/fonts/4x6.bdf
unigui/fonts/Pixelzim-3x5-5.bdf
unigui/fonts/SNES-Italic-24.bdf
unigui/fonts/Silom-Bold-12.bdf
unigui/fonts/Silom-Bold-24.bdf
unigui/fonts/VCROSDMono-14.bdf
unigui/fonts/fipps-12pt.bdf
unigui/fonts/pzim3x5-5.bdf
unigui/images/128x32/px_icons.bmp
unigui/images/256x32/color_blocks.bmp
unigui/images/32x32/blue.bmp
unigui/images/32x32/orange.bmp
unigui/images/32x32/question.bmp
unigui_carstentb-0.1.3.dist-info/LICENSE
unigui_carstentb-0.1.3.dist-info/METADATA
unigui_carstentb-0.1.3.dist-info/WHEEL
unigui_carstentb-0.1.3.dist-info/top_level.txt
unigui_carstentb-0.1.3.dist-info/RECORD
