Metadata-Version: 2.1
Name: unigui-carstentb
Version: 0.1.3
Summary: A cross-hardware GUI framework
Home-page: https://github.com/shulltronics/displayio-universal-ui
Author: Carsten Thue-Bludworth
Author-email: carstentb@protonmail.com
Project-URL: Bug Tracker, https://github.com/shulltronics/displayio-universal-ui/issues
Classifier: Programming Language :: Python :: 3
Classifier: License :: OSI Approved :: MIT License
Classifier: Operating System :: OS Independent
Requires-Python: >=3.9
License-File: LICENSE
Requires-Dist: adafruit-blinka (>=7.3.0)
Requires-Dist: adafruit-blinka-displayio (>=0.10.0)
Requires-Dist: adafruit-circuitpython-display-text (>=2.22.3)
Requires-Dist: adafruit-circuitpython-bitmap-font (>=1.5.6)
Requires-Dist: adafruit-circuitpython-display-shapes (>=2.4.3)
Requires-Dist: adafruit-circuitpython-imageload (>=1.16.0)
Requires-Dist: pygame (>=2.1.2)
